{
	"fetched": 3,
	"records": [
		{
			"attributes": {
				"type": "Course__c",
				"url": "/services/data/v56.0/sobjects/Course__c/a028F000002SPVsQAO"
			},
			"Id": "a028F000002SPVsQAO",
			"Name": "DEX602"
		},
		{
			"attributes": {
				"type": "Course__c",
				"url": "/services/data/v56.0/sobjects/Course__c/a028F000002SPVtQAO"
			},
			"Id": "a028F000002SPVtQAO",
			"Name": "DEX403"
		},
		{
			"attributes": {
				"type": "Course__c",
				"url": "/services/data/v56.0/sobjects/Course__c/a028F000002SPVuQAO"
			},
			"Id": "a028F000002SPVuQAO",
			"Name": "DEX450"
		}
	],
	"total": 3
}